a360_notification/__init__.py
a360_notification/module.py
a360_notification/services/__init__.py
a360_notification/services/aws_ses.py
a360_notification/settings.py
a360_notification/utils/__init__.py
a360_notification/utils/email_utils.py
a360_security/__init__.py
a360_security/depends/__init__.py
a360_security/depends/client_platform.py
a360_security/depends/rbac_voter.py
a360_security/depends/user_dependant.py
a360_security/depends/valid_practice_voter.py
a360_security/dto/__init__.py
a360_security/dto/user.py
a360_security/enums/__init__.py
a360_security/enums/client_platform.py
a360_security/enums/role.py
a360_security/module.py
a360_security/role_hierarchy.py
a360_security/settings.py
a360_security/utils/__init__.py
a360_security/utils/aws_cognito.py
a360_security/utils/bearer.py
a360_services/__init__.py
a360_services/dto/__init__.py
a360_services/dto/service_response.py
a360_services/module.py
a360_services/services/__init__.py
a360_services/services/dict.py
a360_services/services/patient.py
a360_services/services/practice.py
a360_services/settings.py
a360_services/utils/__init__.py
a360_services/utils/service_provider.py
a360_services/utils/services_list.py
a360_utils/__init__.py
a360_utils/module.py
a360_utils/utils/__init__.py
a360_utils/utils/image_magic.py
a360_python_libraries-1.1.0.dist-info/LICENSE
a360_python_libraries-1.1.0.dist-info/METADATA
a360_python_libraries-1.1.0.dist-info/WHEEL
a360_python_libraries-1.1.0.dist-info/RECORD
