Metadata-Version: 2.1
Name: a360-python-libraries
Version: 1.1.0
Summary: A collection of Python libraries for A360
License: Proprietary
Author: A360
Requires-Python: >=3.11,<4.0
Classifier: License :: Other/Proprietary License
Classifier: Programming Language :: Python :: 3
Classifier: Programming Language :: Python :: 3.11
Classifier: Programming Language :: Python :: 3.12
Classifier: Programming Language :: Python :: 3.13
Requires-Dist: boto3 (>=1.35.0,<2.0.0)
Requires-Dist: fastapi (==0.111.0)
Requires-Dist: pydantic (==2.8.2)
Requires-Dist: pydantic-settings (>=2.3.4,<3.0.0)
Requires-Dist: python-jose (>=3.3.0,<4.0.0)
